promissory_note/__init__.py
promissory_note/commands.py
promissory_note/entities.py
promissory_note/events.py
promissory_note/use_cases.py
promissory_note/value_objects.py
promissory_note/gateways/__init__.py
promissory_note/gateways/cli.py
promissory_note/gateways/services.py
promissory_note/gateways/web.py
promissory_note/gateways/static/open_sans.ttf
promissory_note/gateways/static/promissory_note.jpg
promissory_note/gateways/templates/index.html
tests/__init__.py
tests/test_commands.py
tests/test_entities.py
tests/test_events.py
tests/test_use_cases.py
tests/test_value_objects.py
tests/gateways/__init__.py
tests/gateways/test_cli.py
tests/gateways/test_services.py
tests/gateways/test_web.py
promissory_note-0.0.6.dist-info/LICENSE
promissory_note-0.0.6.dist-info/METADATA
promissory_note-0.0.6.dist-info/WHEEL
promissory_note-0.0.6.dist-info/entry_points.txt
promissory_note-0.0.6.dist-info/top_level.txt
promissory_note-0.0.6.dist-info/RECORD
